cipher_encdec/Cipher.py
cipher_encdec/__init__.py
cipher_encdec-0.0.4.dist-info/METADATA
cipher_encdec-0.0.4.dist-info/WHEEL
cipher_encdec-0.0.4.dist-info/top_level.txt
cipher_encdec-0.0.4.dist-info/RECORD
