Metadata-Version: 2.1
Name: cipher-encdec
Version: 0.0.4
Summary: Encodes and Decodes your Data
Home-page: UNKNOWN
Author: Cipher_Secure
License: UNKNOWN
Keywords: python,cipher
Platform: UNKNOWN
Classifier: Intended Audience :: Developers
Classifier: Programming Language :: Python :: 3
Classifier: Operating System :: Unix
Classifier: Operating System :: MacOS :: MacOS X
Classifier: Operating System :: Microsoft :: Windows
